sfz/__init__.py
sfz/code.py
sfz-0.0.2.dist-info/METADATA
sfz-0.0.2.dist-info/RECORD
sfz-0.0.2.dist-info/WHEEL
sfz-0.0.2.dist-info/top_level.txt
