Metadata-Version: 2.1
Name: sfz
Version: 0.0.2
Summary: A simple Package to deal with Mainland ID Card Number.（一个用来处理大陆身份证号码的小包）。
Home-page: https://github.com/n0vad3v/sfz
Author: Nova Kwok
Author-email: n0vad3v@riseup.net
License: UNKNOWN
Platform: UNKNOWN
Classifier: Programming Language :: Python :: 3
Classifier: License :: OSI Approved :: GNU General Public License v3 (GPLv3)
Classifier: Operating System :: OS Independent
